client/__init__.py
client/cmdmate_apiClient.py
client/cmdmate_cli.py
client/cmdmate_client.py
cmdmate-0.1.7.dist-info/licenses/LICENSE
cmdmate-0.1.7.dist-info/METADATA
cmdmate-0.1.7.dist-info/WHEEL
cmdmate-0.1.7.dist-info/entry_points.txt
cmdmate-0.1.7.dist-info/top_level.txt
cmdmate-0.1.7.dist-info/RECORD
