Metadata-Version: 2.4
Name: cmdmate
Version: 0.1.7
Summary: cmdmate : Your AI powered terminal assistant 🚀
Author: Chinmay Rao
License: MIT
Project-URL: Homepage, https://github.com/mmchinmay555/cmdmate
Project-URL: Repository, https://github.com/mmchinmay555/cmdmate
Requires-Python: <3.14,>=3.8
License-File: LICENSE
Requires-Dist: requests<3,>=2.31
Dynamic: license-file
